pyperscan-0.3.0.dist-info/METADATA
pyperscan-0.3.0.dist-info/WHEEL
pyperscan-0.3.0.dist-info/license_files/LICENSE-APACHE
pyperscan-0.3.0.dist-info/license_files/LICENSE-MIT
pyperscan/_pyperscan.pyi
pyperscan/__init__.py
pyperscan/py.typed
pyperscan/_pyperscan.abi3.so
pyperscan-0.3.0.dist-info/RECORD
