Metadata-Version: 2.1
Name: pyperscan
Version: 0.3.0
License-File: LICENSE-APACHE
License-File: LICENSE-MIT
Author: László Vaskó <1771332+vlaci@users.noreply.github.com>
Author-email: László Vaskó <1771332+vlaci@users.noreply.github.com>
License: MIT OR Apache-2.0
Requires-Python: >=3.8
Project-URL: Homepage, https://vlaci.github.io/pyperscan
Project-URL: Repository, https://github.com/vlaci/pyperscan
Project-URL: Changelog, https://github.com/vlaci/pyperscan/blob/main/CHANGELOG.md
